pipestat_reader/__init__.py
pipestat_reader/_version.py
pipestat_reader/const.py
pipestat_reader/graphql.py
pipestat_reader-0.0.3.dist-info/METADATA
pipestat_reader-0.0.3.dist-info/WHEEL
pipestat_reader-0.0.3.dist-info/top_level.txt
pipestat_reader-0.0.3.dist-info/RECORD
