Metadata-Version: 2.1
Name: pipestat_reader
Version: 0.0.3
Summary: A generator of pipestat-based APIs
Home-page: https://github.com/pepkit/pipestat_reader
Author: Michal Stolarczyk
License: BSD2
Keywords: project,metadata,bioinformatics,sequencing,ngs,workflow
Classifier: Development Status :: 4 - Beta
Classifier: License :: OSI Approved :: BSD License
Classifier: Programming Language :: Python :: 3.6
Classifier: Programming Language :: Python :: 3.7
Classifier: Programming Language :: Python :: 3.8
Classifier: Programming Language :: Python :: 3.9
Classifier: Topic :: Scientific/Engineering :: Bio-Informatics
